mle_decoder/__init__.py
mle_decoder/decoder.py
mle_decoder-0.2.1.dist-info/licenses/LICENSE
mle_decoder-0.2.1.dist-info/METADATA
mle_decoder-0.2.1.dist-info/WHEEL
mle_decoder-0.2.1.dist-info/top_level.txt
mle_decoder-0.2.1.dist-info/RECORD
