Metadata-Version: 2.4
Name: mle_decoder
Version: 0.2.1
Summary: Most-likely error (MLE) decoder that uses gurobi to solve the mixed-interger (linear) programming problem
Author-email: Marc Serra Peralta <marcserraperalta@gmail.com>
Maintainer-email: Marc Serra Peralta <marcserraperalta@gmail.com>
License: MIT License
Keywords: MLE,decoder,quantum error correction,qec
Requires-Python: >=3.10
License-File: LICENSE
Requires-Dist: numpy
Requires-Dist: stim
Requires-Dist: gurobipy
Requires-Dist: scipy
Provides-Extra: dev
Requires-Dist: pip-tools; extra == "dev"
Requires-Dist: pytest; extra == "dev"
Requires-Dist: black; extra == "dev"
Requires-Dist: pytest-black; extra == "dev"
Requires-Dist: flake8; extra == "dev"
Requires-Dist: flake8-print; extra == "dev"
Requires-Dist: pytest-flake8; extra == "dev"
Requires-Dist: gprof2dot; extra == "dev"
Dynamic: license-file
